codeformer_kit/__init__.py
codeformer_kit/codeformer.py
codeformer_kit/archs/__init__.py
codeformer_kit/archs/arch_util.py
codeformer_kit/archs/codeformer_arch.py
codeformer_kit/archs/vqgan_arch.py
codeformer_kit/ops/__init__.py
codeformer_kit/ops/dcn/__init__.py
codeformer_kit/ops/dcn/deform_conv.py
codeformer_kit/utils/__init__.py
codeformer_kit/utils/dist_util.py
codeformer_kit/utils/logger.py
codeformer_kit/utils/misc.py
codeformer_kit/utils/registry.py
codeformer_kit-0.0.8.dist-info/METADATA
codeformer_kit-0.0.8.dist-info/WHEEL
codeformer_kit-0.0.8.dist-info/top_level.txt
codeformer_kit-0.0.8.dist-info/RECORD
