Metadata-Version: 2.1
Name: codeformer_kit
Version: 0.0.8
Summary: Unstructured set of the helper functions.
Home-page: https://github.com/datvtn/codeformer_kit
Author: Dat Viet Thanh Nguyen
License: MIT
Classifier: License :: OSI Approved :: MIT License
Classifier: Intended Audience :: Developers
Classifier: Intended Audience :: Science/Research
Classifier: Operating System :: OS Independent
Classifier: Programming Language :: Python
Classifier: Programming Language :: Python :: 3
Classifier: Topic :: Software Development :: Libraries
Classifier: Topic :: Software Development :: Libraries :: Python Modules
Requires-Dist: numpy ==1.24.3
Requires-Dist: Pillow
Requires-Dist: opencv-python
Requires-Dist: torch ==2.4.0
Requires-Dist: torchvision ==0.19.0
Requires-Dist: datvtn-kit
Requires-Dist: datvtn-nn-kit
Provides-Extra: test
Requires-Dist: pytest ; extra == 'test'
